writefreely/__init__.py
writefreely/client.py
writefreely_py-1.2.0.dist-info/LICENSE
writefreely_py-1.2.0.dist-info/METADATA
writefreely_py-1.2.0.dist-info/WHEEL
writefreely_py-1.2.0.dist-info/top_level.txt
writefreely_py-1.2.0.dist-info/RECORD
