Metadata-Version: 2.1
Name: writefreely-py
Version: 1.2.0
Summary: A Python package wrapping the WriteFreely / Write.as API
Home-page: https://github.com/adbenitez/writefreely-py
Author: adbenitez
Author-email: adbenitez@nauta.cu
License: MIT
Platform: UNKNOWN
Classifier: Development Status :: 4 - Beta
Classifier: Intended Audience :: Developers
Classifier: License :: OSI Approved :: MIT License
Classifier: Operating System :: OS Independent
Classifier: Programming Language :: Python :: 3
Requires-Python: >=3.5
Requires-Dist: requests (>=2.26.0)
Provides-Extra: dev
Requires-Dist: requests (>=2.26.0) ; extra == 'dev'
Requires-Dist: pytest (>=6.2.5) ; extra == 'dev'
Requires-Dist: requests-mock (>=1.9.3) ; extra == 'dev'
Requires-Dist: black (>=21.8b0) ; extra == 'dev'
Requires-Dist: mypy (>=0.910) ; extra == 'dev'
Requires-Dist: isort (>=5.9.3) ; extra == 'dev'
Requires-Dist: pylint (>=2.10.2) ; extra == 'dev'
Requires-Dist: pylama (>=7.7.1) ; extra == 'dev'
Requires-Dist: types-pkg-resources (>=0.1.3) ; extra == 'dev'
Requires-Dist: types-requests (>=2.25.6) ; extra == 'dev'
Provides-Extra: test
Requires-Dist: pytest (>=6.2.5) ; extra == 'test'
Requires-Dist: requests-mock (>=1.9.3) ; extra == 'test'
